{
  "users": [
    {
      "firstName": "Salaheddine",
      "lastName": "Moussaoui",
      "email": "salah.moussaoui@outlook.com",
      "profileImage": "",
      "coverImage": "",
      "id": 1
    }
  ],
  "clubs": [
    {
      "name": "IEEE ENSA Fès",
      "primaryColor": "#2196f3",
      "profileImage": "",
      "coverImage": "",
      "id": 1
    }
  ],
  "posts": [
    {
      "id": 1,
      "text": "hello",
      "image": "",
      "creationDateTime": "",
      "userId": 1,
      "clubId": 1
    },
    {
      "text": "te",
      "image": "",
      "clubId": 1,
      "userId": 1,
      "creationDateTime": "",
      "id": 2
    }
  ],
  "roles": [
    {
      "id": 1,
      "name": "Editeur",
      "canInvite": true,
      "canRemove": true,
      "canPost": true,
      "canEdit": true,
      "isDefault": true,
      "clubId": 1
    }
  ],
  "members": [
    {
      "userId": 1,
      "clubId": 1,
      "type": "member",
      "roleId": 1
    }
  ],
  "comments": [
    {
      "id": 1,
      "text": "interessant!",
      "creationDateTime": "",
      "postId": 1,
      "userId": 1
    },
    {
      "id": 2,
      "text": "interessant!",
      "creationDateTime": "",
      "postId": 1,
      "userId": 1
    },
    {
      "id": 3,
      "text": "interessant!",
      "creationDateTime": "",
      "postId": 1,
      "userId": 1
    },
    {
      "id": 4,
      "text": "interessant!",
      "creationDateTime": "",
      "postId": 1,
      "userId": 1
    },
    {
      "text": "test",
      "postId": 1,
      "userId": 1,
      "creationDateTime": "",
      "id": 5
    },
    {
      "text": "aze",
      "postId": 1,
      "userId": 1,
      "creationDateTime": "",
      "id": 6
    },
    {
      "text": "aze",
      "postId": 1,
      "userId": 1,
      "creationDateTime": "",
      "id": 7
    },
    {
      "text": "gfd",
      "postId": 1,
      "userId": 1,
      "creationDateTime": "",
      "id": 8
    }
  ],
  "auth": [
    {
      "token": "oijrpekg",
      "userId": 1
    }
  ]
}